Workbook

Sheet Materialidade
A1: PT 320 — Materialidade (R$ mil) — fórmulas
A2: Preparador: matrícula 231020069 (assistido por IA) | Data: 22/10/2026 | Revisão: ____ (sem revisão de terceiros simulada)
A3: Bases reconferidas na DF25 em 22/10/2026 (B02). Percentuais = julgamento didático (NBC TA 320 item A8 dá 5% do lucro antes do imposto como EXEMPLO, não como regra). Células amarelas são entradas; as demais, fórmulas.
A4: Item | B4: Valor | C4: Unidade | D4: Fonte / natureza | E4: Observação
A5: Lucro antes dos tributos (LAIR) | B5: 8091246 | C5: R$ mil | D5: DF25 p. 36/4 (DRE) e p. 39/7 (DFC) | E5: Base principal: companhia lucrativa e estável (LAIR 2024: 8.088.893)
A6: Receita operacional líquida | B6: 44367780 | C6: R$ mil | D6: DF25 p. 36/4 | E6: Base alternativa
A7: Ativo total | B7: 81099930 | C7: R$ mil | D7: DF25 p. 34/2 | E7: Base alternativa (intensiva em capital)
A8: Patrimônio líquido total | B8: 23504510 | C8: R$ mil | D8: DF25 p. 35/3 | E8: Base alternativa (referência)
A9: Ajuste ao valor justo VNR (nota 11) | B9: 1285173 | C9: R$ mil | D9: DF25 p. 68/36 | E9: Componente não caixa do resultado
A10: % sobre LAIR | B10: 0.05 | C10: % | D10: Julgamento (exemplo em 320 A8)
A11: % sobre receita | B11: 0.005 | C11: % | D11: Julgamento
A12: % sobre ativo | B12: 0.005 | C12: % | D12: Julgamento
A13: % sobre PL | B13: 0.01 | C13: % | D13: Julgamento
A14: % execução / global | B14: 0.75 | C14: % | D14: Julgamento (aprovado na etapa 2) | E14: Mantido: sem histórico de distorções conhecido; relatório sem modificação. Sensibilidade abaixo
A15: % trivial / global | B15: 0.05 | C15: % | D15: Julgamento (limite operacional NBC TA 450)
A17: Materialidade pelo LAIR | B17: =B5*B10 -> 404562.3 | C17: R$ mil | D17: fórmula
A18: Materialidade pela receita | B18: =B6*B11 -> 221838.9 | C18: R$ mil | D18: fórmula
A19: Materialidade pelo ativo | B19: =B7*B12 -> 405499.65 | C19: R$ mil | D19: fórmula
A20: Materialidade pelo PL | B20: =B8*B13 -> 235045.1 | C20: R$ mil | D20: fórmula
A21: MATERIALIDADE GLOBAL SELECIONADA (LAIR) | B21: =B17 -> 404562.3 | C21: R$ mil | D21: fórmula
A22: Materialidade para execução | B22: =B21*B14 -> 303421.72 | C22: R$ mil | D22: fórmula
A23: Limite de distorções claramente triviais | B23: =B21*B15 -> 20228.115 | C23: R$ mil | D23: fórmula
A24: LAIR sem ajuste VNR (sensibilidade mecânica) | B24: =B5-B9 -> 6806073 | C24: R$ mil | D24: fórmula
A25: Materialidade sensibilidade VNR | B25: =B24*B10 -> 340303.65 | C25: R$ mil | D25: fórmula
A26: Diferença vs. global | B26: =B21-B25 -> 64258.65 | C26: R$ mil | D26: fórmula
A27: Execução a 60% (sensibilidade) | B27: =B21*0.6 -> 242737.38 | C27: R$ mil | D27: fórmula
A28: Execução a 50% (sensibilidade) | B28: =B21*0.5 -> 202281.15 | C28: R$ mil | D28: fórmula
A29: Estoques / materialidade global | B29: =236566/B21 -> 0.58474554 | C29: x | D29: fórmula
A30: Caixa e equivalentes / materialidade global | B30: =2229320/B21 -> 5.5104492 | C30: x | D30: fórmula
A32: Materialidade específica (item 10): não se fixa valor quantitativo inferior para nenhuma classe. Fundamento: as divulgações sensíveis (remuneração da administração, partes relacionadas — PT 550) são avaliadas qualitativamente (NBC TA 450), e as estimativas de maior risco já recebem resposta substantiva extensiva (PT 330). Reavaliar se o PT 550 identificar transações com o controlador sensíveis aos usuários.
A33: Gatilhos de revisão (item 12–13): (i) distorções acumuladas acima de 50% da execução; (ii) evento subsequente que altere o LAIR (ex.: renovação das concessões afetando o VNR); (iii) reapresentação de 2024 identificada no PT 510.
A34: Documentação (item 14): valores e fatores registrados nesta aba e no PT 320.

Sheet Matriz_Riscos_315
A1: PT 315 — Matriz de riscos por conta e afirmação (NBC TA 315 R2)
A2: Preparador: matrícula 231020069 (assistido por IA) | Data: 22/10/2026 | Revisão: ____ (sem revisão de terceiros simulada)
A3: *C = complexidade; S = subjetividade; M = mudança; I = incerteza; V = suscetibilidade a viés/fraude (315 item 12(f)). Pontuação e nível = proxy didática do espectro de risco inerente (315 item 31), não fórmula da norma. Risco de controle: sem teste de efetividade, o risco de distorção relevante = risco inerente (315 item 34). Revisão da matriz preliminar da etapa 3 (17 riscos) + R18 e R19.
A4: ID | B4: Conta / processo | C4: Saldo 2025 (R$ mil) | D4: Fonte | E4: Afirmações | F4: Risco | G4: Fatores de risco inerente* | H4: Prob. (1-3) | I4: Magn. (1-3) | J4: Pontuação | K4: Nível (espectro) | L4: Risco significativo? | M4: Fundamento | N4: Saldo / MG | O4: Risco de controle
A5: R01 | B5: Ativo financeiro da concessão (nota 11) | C5: 29623619 | D5: DF25 p. 34/2; p. 68/36; PAA 3 p. 29 | E5: Avaliação; classificação; apresentação | F5: Mensuração a VNR e bifurcação (ativo financeiro × contratual × intangível) incorretas | G5: C,S,I,V | H5: 3 | I5: 3 | J5: =H5*I5 -> 9 | K5: Alto | L5: Sim | M5: Estimativa com alta incerteza; PAA 3; 36,5% do ativo; ajuste VNR de 1.285.173 = 15,9% do LAIR | N5: =C5/Materialidade!$B$21 -> 73.223874 | O5: Não testado → RDR = risco inerente (315 item 34)
A6: R02 | B6: Ativo contratual (transmissão e distribuição) | C6: 12859523 | D6: DF25 p. 34/2; nota 15 p. 76; PAA 1 p. 27 | E6: Avaliação; exatidão | F6: Taxa de desconto, margens e RAP distorcem ativo e receita de remuneração | G6: C,S,I | H6: 3 | I6: 3 | J6: =H6*I6 -> 9 | K6: Alto | L6: Sim | M6: Estimativa de longo prazo; PAA 1 | N6: =C6/Materialidade!$B$21 -> 31.786261 | O6: Não testado → RDR = risco inerente (315 item 34)
A7: R03 | B7: Receita não faturada | C7: 1763858 | D7: DF25 p. 28 (PAA 2); nota 3.11 p. 54 | E7: Ocorrência; corte; exatidão | F7: Estimativa baseada em carga, faturamento e perdas técnicas/comerciais; depende de TI | G7: C,S,I,V | H7: 3 | I7: 3 | J7: =H7*I7 -> 9 | K7: Alto | L7: Sim | M7: PAA 2; dados de sistemas; presunção de fraude em receita (240 item 27) | N7: =C7/Materialidade!$B$21 -> 4.3599169 | O7: Não testado → RDR = risco inerente (315 item 34)
A8: R04 | B8: Receita operacional líquida (demais componentes) | C8: 44367780 | D8: DF25 p. 36/4; nota 26 p. 100–101 | E8: Ocorrência; corte; exatidão; classificação | F8: Componentes regulados (tarifa, CDE R$ 3.103.700, construção R$ 5.879.424) registrados incorretamente | G8: C,M,V | H8: 2 | I8: 3 | J8: =H8*I8 -> 6 | K8: Moderado | L8: Não (ver R03) | M8: Receita tarifária homologada pela ANEEL reduz discricionariedade; risco de fraude concentrado em R03 e comercialização | N8: =C8/Materialidade!$B$21 -> 109.6686 | O8: Não testado → RDR = risco inerente (315 item 34)
A9: R05 | B9: Consumidores, concessionárias e permissionárias | C9: 6377562 | D9: DF25 p. 34/2; nota 7 p. 61 | E9: Existência; avaliação (PDD) | F9: Perdas esperadas insuficientes; PDD de 361.253 em 2025 | G9: S,I | H9: 2 | I9: 3 | J9: =H9*I9 -> 6 | K9: Moderado | L9: Não | M9: Estimativa com histórico e regras regulatórias | N9: =C9/Materialidade!$B$21 -> 15.764104 | O9: Não testado → RDR = risco inerente (315 item 34)
A10: R06 | B10: Empréstimos, financiamentos e debêntures | C10: 29055727 | D10: DF25 p. 35/3; notas 18–19 p. 79–85 | E10: Integridade; exatidão; classificação CP/LP; divulgação | F10: Classificação e encargos incorretos; covenants (cross default) — administração declara cumprimento | G10: C,M | H10: 2 | I10: 3 | J10: =H10*I10 -> 6 | K10: Moderado | L10: Não | M10: Liquidação antecipada de 5.616.000 em debêntures e captações de 10.266.269 em 2025 (p. 39, 85) | N10: =C10/Materialidade!$B$21 -> 71.820155 | O10: Não testado → RDR = risco inerente (315 item 34)
A11: R07 | B11: Provisões fiscais, cíveis, trabalhistas e regulatórias | C11: 1740903 | D11: DF25 p. 35/3; nota 22 p. 94–96 | E11: Integridade; avaliação; divulgação | F11: Classificação provável/possível e mensuração subavaliadas | G11: S,I,V | H11: 2 | I11: 3 | J11: =H11*I11 -> 6 | K11: Moderado | L11: Não | M11: Julgamento jurídico | N11: =C11/Materialidade!$B$21 -> 4.3031765 | O11: Não testado → RDR = risco inerente (315 item 34)
A12: R08 | B12: Derivativos (ativos 595.863; passivos 403.394) | C12: 595863 | D12: DF25 p. 34–35; nota 34 p. 108 | E12: Avaliação; apresentação | F12: Valor justo e hedge contábil incorretos | G12: C,S | H12: 2 | I12: 2 | J12: =H12*I12 -> 4 | K12: Moderado | L12: Não | M12: Correção da matriz preliminar: 999.257 somava ativos e passivos (DV17) | N12: =C12/Materialidade!$B$21 -> 1.4728584 | O12: Não testado → RDR = risco inerente (315 item 34)
A13: R09 | B13: Ativos e passivos financeiros setoriais | C13: 2402307 | D13: DF25 p. 34/2; nota 9 p. 64 | E13: Avaliação; classificação | F13: Componentes tarifários e prazos de recuperação incorretos | G13: C,M,I | H13: 2 | I13: 3 | J13: =H13*I13 -> 6 | K13: Moderado | L13: Não | M13: Dependem de atos ANEEL (ex.: REH 3.452/2025, nota 26.2) | N13: =C13/Materialidade!$B$21 -> 5.9380397 | O13: Não testado → RDR = risco inerente (315 item 34)
A14: R10 | B14: Imobilizado e intangível | C14: 16268718 | D14: DF25 p. 34/2; notas 14 e 16 p. 75–78 | E14: Existência; avaliação; classificação | F14: Capitalização indevida; vidas úteis; amortização do intangível da concessão (332.792) | G14: S | H14: 2 | I14: 2 | J14: =H14*I14 -> 4 | K14: Moderado | L14: Não | M14: Sem provisão de recuperação em 2025 (nota 14) | N14: =C14/Materialidade!$B$21 -> 40.213134 | O14: Não testado → RDR = risco inerente (315 item 34)
A15: R11 | B15: Caixa e equivalentes | C15: 2229320 | D15: DF25 p. 34/2; nota 5 p. 60 | E15: Existência; direitos | F15: Saldos inexistentes ou restritos | G15: — | H15: 1 | I15: 2 | J15: =H15*I15 -> 2 | K15: Baixo | L15: Não | M15: Alta verificabilidade externa | N15: =C15/Materialidade!$B$21 -> 5.5104492 | O15: Não testado → RDR = risco inerente (315 item 34)
A16: R12 | B16: Estoques | C16: 236566 | D16: DF25 p. 34/2 | E16: Existência; avaliação | F16: Quantidades e obsolescência | G16: — | H16: 1 | I16: 1 | J16: =H16*I16 -> 1 | K16: Baixo | L16: Não | M16: 0,3% do ativo; 58% da materialidade global — abaixo dela isoladamente | N16: =C16/Materialidade!$B$21 -> 0.58474554 | O16: Não testado → RDR = risco inerente (315 item 34)
... A18: R14 | B18: Consolidação do grupo | C18: 81099930 | D18: DF25 nota 1 p. 41–42; nota 13 p. 69 | E18: Integridade; apresentação | F18: Eliminações e componentes incorretos; julgamento de controle conjunto da Chapecoense (51%, acordo de acionistas — nota 13.9.3, p. 74) | G18: C | H18: 2 | I18: 3 | J18: =H18*I18 -> 6 | K18: Moderado | L18: Não | M18: Grupo com 4 distribuidoras, geração, transmissão e comercialização | N18: =C18/Materialidade!$B$21 -> 200.46339 | O18: Não testado → RDR = risco inerente (315 item 34)
A19: R15 | B19: TI — medição, faturamento e interfaces | C19: — | D19: DF25 p. 28 (PwC usou especialistas de TI) | E19: Integridade; exatidão; corte | F19: Dados de origem e interfaces incorretos | G19: C | H19: 2 | I19: 3 | J19: =H19*I19 -> 6 | K19: Moderado | L19: Não | M19: Afeta R03; controles não testados | N19: — | O19: Não testado → RDR = risco inerente (315 item 34)
A20: R16 | B20: Burla de controles pela administração | C20: — | D20: NBC TA 240 item 32 | E20: Todas | F20: Lançamentos manuais, estimativas enviesadas, transações incomuns | G20: V | H20: 2 | I20: 3 | J20: =H20*I20 -> 6 | K20: Alto | L20: Sim | M20: Risco significativo por exigência da NBC TA 240 (item 28 e item 32) | N20: — | O20: Não testado → RDR = risco inerente (315 item 34)
A21: R17 | B21: Continuidade e liquidez | D21: DF25 p. 34–35; p. 39/7 | E21: Divulgação | F21: Liquidez corrente 0,93; serviço da dívida | G21: I | H21: 1 | I21: 3 | J21: =H21*I21 -> 3 | K21: Baixo | L21: Não | M21: Caixa operacional 7.162.797; LL 5.742.552; covenants cumpridos segundo a administração (p. 83, 85) | N21: — | O21: Não testado → RDR = risco inerente (315 item 34)
A22: R18 | B22: Renovação das concessões (premissa do ativo financeiro) | D22: Fato Relevante 08/05/2026; fatos relevantes de 28/03/2025 citados | E22: Avaliação; divulgação | F22: Premissa de indenização ao fim da concessão afetada pela prorrogação de 30 anos | G22: S,M,I | H22: 2 | I22: 3 | J22: =H22*I22 -> 6 | K22: Moderado | L22: Não (vinculado a R01) | M22: Processo iniciado em 2025; aditivos assinados em 2026 — analisar no PT 540/560 | N22: — | O22: Não testado → RDR = risco inerente (315 item 34)
A23: R19 | B23: PIS/COFINS sobre ICMS — créditos e devolução a consumidores | D23: DF25 p. 34–35; nota 8 p. 62–63 | E23: Avaliação; classificação; divulgação | F23: Ativo 4.096.542 e passivo 3.402.844 mal mensurados ou classificados | G23: C,M | H23: 2 | I23: 3 | J23: =H23*I23 -> 6 | K23: Moderado | L23: Não | M23: Saldos relevantes ligados a decisões judiciais (STF tema 69) | N23: — | O23: Não testado → RDR = risco inerente (315 item 34)

Sheet Respostas_330
A1: PT 330 — Respostas aos riscos avaliados (natureza, época, extensão, modalidade)
A2: Preparador: matrícula 231020069 (assistido por IA) | Data: 22/10/2026 | Revisão: ____ (sem revisão de terceiros simulada)
A3: Respostas gerais (330 item 5): ceticismo reforçado em estimativas, imprevisibilidade na seleção (amostragem aleatória com semente registrada), reconferência de toda fonte secundária. Riscos significativos (R01, R02, R03, R16): procedimentos substantivos específicos (330 item 21). Época 'interina' é planejada; nada foi executado na companhia.
A4: Risco | B4: Procedimento | C4: Natureza | D4: Época | E4: Extensão | F4: Modalidade | G4: PT
A5: R01 | B5: Reexecutar a movimentação da nota 11 e conciliar com BP, DRE (ajuste VNR na receita) e DFC | C5: Substantivo — recálculo | D5: Final | E5: 100% da movimentação | F5: Realizado com evidência pública (B02: CC05/CC06) | G5: 500
A6: R01 | B6: Testar existência e valor de bens na base de remuneração por amostragem (MUS) | C6: Substantivo — detalhe | D6: Final | E6: Amostra estatística sobre população de 500.000 registros | F6: Simulado para fins didáticos | G6: 530
A7: R01 | B7: Avaliar método, premissas (VNR, índices) e viés; sensibilidade | C7: Substantivo — estimativa | D7: Final | E7: Premissas-chave | F7: Realizado com evidência pública + simulação | G7: 540
A8: R01 | B8: Inspecionar laudos de avaliação e base de remuneração homologada pela ANEEL | C8: Substantivo — inspeção | D8: Final | E8: Distribuidoras relevantes | F8: Planejado por falta de acesso | G8: 540
A9: R02 | B9: Ler contratos de concessão e RAP; recalcular remuneração com dados públicos | C9: Substantivo | D9: Final | E9: Lote principal | F9: Planejado (contratos parcialmente no Drive) | G9: 540
A10: R02 | B10: Analítico: receita de remuneração/ativo contratual médio | C10: Analítico substantivo | D10: Final | E10: Por segmento | F10: Realizado com evidência pública | G10: 520
A11: R03 | B11: Recalcular receita não faturada (carga cativa × tarifas por classe) | C11: Substantivo — recálculo | D11: Final | E11: Por distribuidora | F11: Planejado por falta de acesso | G11: 540
A12: R03 | B12: Comparar faturamento de janeiro/2026 com estimativa de dezembro/2025 (corte) | C12: Substantivo — eventos subsequentes | D12: Após fechamento | E12: Total | F12: Planejado por falta de acesso | G12: 560
A13: R03 | B13: Testar controles de TI (ITGC) de medição e faturamento | C13: Teste de controles | D13: Interina | E13: Sistemas-chave | F13: Planejado por falta de acesso | G13: 330/402
A14: R04 | B14: Analítico de receita por componente (tarifa, CDE, construção, VNR) 2025 × 2024 | C14: Analítico substantivo | D14: Final | E14: Componentes da nota 26 | F14: Realizado com evidência pública | G14: 520
A15: R04 | B15: Conciliar receita de construção com adições de ativo contratual (DFC 4.963.868) | C15: Substantivo | D15: Final | E15: Total | F15: Realizado com evidência pública | G15: 520
... A37: R19 | B37: Ler nota 8; conciliar ativo e passivo de PIS/COFINS; analisar compensações | C37: Substantivo | D37: Final | E37: Saldos consolidados | F37: Realizado com evidência pública (parcial) | G37: 500/520

Sheet Programas_Ciclos
A1: Programas de auditoria por ciclo (PT 300/330)
A2: Preparador: matrícula 231020069 (assistido por IA) | Data: 22/10/2026 | Revisão: ____ (sem revisão de terceiros simulada)
A3: Legenda: [Pub] realizado com evidência pública; [P] planejado por falta de acesso; [S] simulado. O estado de execução de cada procedimento é atualizado nos blocos seguintes.
A4: Código | B4: Ciclo | C4: Riscos | D4: Saldo-base | E4: Aplicabilidade e extensão | F4: Procedimento | G4: Nº
A5: PG-REC | B5: Receitas | C5: R03, R04, R15, R16 | D5: 44.367.780 (DRE p. 36/4) | E5: Aplicável — maior classe de transações; presunção de fraude | F5: Analítico por componente da nota 26 (expectativa: variação tarifária + mercado) [Pub] — PT 520 | G5: 1
A6: PG-REC | B6: Receitas | C6: R03, R04, R15, R16 | D6: 44.367.780 (DRE p. 36/4) | E6: Aplicável — maior classe de transações; presunção de fraude | F6: Conciliar receita de construção × adições de ativo contratual e intangível [Pub] — PT 520 | G6: 2
A7: PG-REC | B7: Receitas | C7: R03, R04, R15, R16 | D7: 44.367.780 (DRE p. 36/4) | E7: Aplicável — maior classe de transações; presunção de fraude | F7: Recalcular receita não faturada e testar corte com faturamento subsequente [P] — PT 540/560 | G7: 3
A8: PG-REC | B8: Receitas | C8: R03, R04, R15, R16 | D8: 44.367.780 (DRE p. 36/4) | E8: Aplicável — maior classe de transações; presunção de fraude | F8: Testar ITGC de medição/faturamento e controles de interface [P] — PT 330/402 | G8: 4
A9: PG-REC | B9: Receitas | C9: R03, R04, R15, R16 | D9: 44.367.780 (DRE p. 36/4) | E9: Aplicável — maior classe de transações; presunção de fraude | F9: Teste de lançamentos contábeis em contas de receita (critérios: manuais, fim de período, valores redondos) [P] — PT 240 | G9: 5
A10: PG-DISP | B10: Disponibilidades | C10: R11 | D10: 2.229.320 + TVM 675.762 (BP p. 34/2) | E10: Aplicável — saldo acima da materialidade global; risco baixo | F10: Conferir caixa da DFC × BP [Pub — feito no B02, CC03] — PT 500 | G10: 1
A11: PG-DISP | B11: Disponibilidades | C11: R11 | D11: 2.229.320 + TVM 675.762 (BP p. 34/2) | E11: Aplicável — saldo acima da materialidade global; risco baixo | F11: Confirmação bancária: modelo e controle de circularização (não enviado) [S/P] — PT 505 | G11: 2
A12: PG-DISP | B12: Disponibilidades | C12: R11 | D12: 2.229.320 + TVM 675.762 (BP p. 34/2) | E12: Aplicável — saldo acima da materialidade global; risco baixo | F12: Conciliações bancárias e extratos de janeiro/2026 [P] — PT 505 | G12: 3
A13: PG-DISP | B13: Disponibilidades | C13: R11 | D13: 2.229.320 + TVM 675.762 (BP p. 34/2) | E13: Aplicável — saldo acima da materialidade global; risco baixo | F13: Verificar restrições e garantias (cauções, nota 12) [Pub] — PT 500 | G13: 4
A14: PG-EST | B14: Estoques | C14: R12 | D14: 236.566 (BP p. 34/2) | E14: Aplicabilidade limitada — 58% da materialidade global; 0,3% do ativo | F14: Analítico de variação 2025 × 2024 (+6,8%) [Pub] — PT 520 | G14: 1
A15: PG-EST | B15: Estoques | C15: R12 | D15: 236.566 (BP p. 34/2) | E15: Aplicabilidade limitada — 58% da materialidade global; 0,3% do ativo | F15: Análise qualitativa: materiais de manutenção da distribuição; ausência de PAA [Pub] — PT 501 | G15: 2
A16: PG-EST | B16: Estoques | C16: R12 | D16: 236.566 (BP p. 34/2) | E16: Aplicabilidade limitada — 58% da materialidade global; 0,3% do ativo | F16: Acompanhamento de inventário apenas se o risco aumentar (NBC TA 501 item 4) [P] — PT 501 | G16: 3
... A31: PG-ESTIM | B31: Estimativas | C31: R01, R02, R03, R05, R07, R08, R18 | D31: AFC 29.623.619; ativo contratual 12.859.523; não faturada 1.763.858 | E31: Aplicável — três PAA são estimativas | F31: Avaliar indicadores de viés da administração [Pub] — PT 540 | G31: 5

Sheet Fraude_240
A1: PT 240 — Fatores de risco de fraude (NBC TA 240 R1)
A2: Preparador: matrícula 231020069 (assistido por IA) | Data: 22/10/2026 | Revisão: ____ (sem revisão de terceiros simulada)
A3: Classificação dos fatores conforme a NBC TA 240. Fator de risco não é alegação de fraude.
A4: Categoria | B4: Fator | C4: Fonte | D4: Natureza
A5: Incentivo/pressão | B5: Remuneração e metas vinculadas a lucro e EBITDA; covenants financeiros (cross default) | C5: Notas 18–19 p. 82–85 (covenants); FR item 8 indisponível (truncado) | D5: Inferência
A6: Incentivo/pressão | B6: Dividendos relevantes ao controlador (dividendos pagos 3.519.769 em 2025) | C6: DF25 p. 39/7 | D6: Fato
A7: Oportunidade | B7: Estimativas complexas com alta subjetividade (VNR, receita não faturada, ativo contratual) | C7: PAA 1–3, DF25 p. 27–29 | D7: Fato
A8: Oportunidade | B8: Transações com o controlador (mútuos de 4.412.650) | C8: DF25 p. 35/3; nota 31 | D8: Fato
A9: Oportunidade | B9: Grupo complexo, com controladas em conjunto e reorganizações (incorporação da CPFL Geração em 2026) | C9: Nota 1 p. 41–42; nota 37.1 p. 113 | D9: Fato
A10: Atitude/racionalização | B10: Sem indícios públicos identificados; não testável sem acesso (entrevistas) | C10: — | D10: Não avaliável
A11: Fator mitigador (não elimina o risco) | B11: Comitê de Auditoria e Conselho Fiscal com regimentos publicados; Novo Mercado; auditoria por firma de grande porte | C11: Drive pasta 03 (regimentos 2025/2026); FR 2025 item 1.1 | D11: Fato

Sheet Leis_250
A1: PT 250 — Mapa de leis e regulamentos
A2: Preparador: matrícula 231020069 (assistido por IA) | Data: 22/10/2026 | Revisão: ____ (sem revisão de terceiros simulada)
A3: Mapeamento para fins de auditoria; não é parecer jurídico.
A4: Categoria (250 itens 14–15) | B4: Lei / regulamento | C4: Fonte | D4: Efeito nas DF | E4: Procedimento e modalidade
A5: Efeito direto | B5: Lei 6.404/76 e Resoluções CVM (estrutura contábil; CPC aprovados pela CVM) | C5: DF25 nota 2.1 p. 45 | D5: Elaboração e divulgação | E5: Ler DF e conferir aderência de divulgações-chave [Pub]
A6: Efeito direto | B6: Regulação tarifária ANEEL (PRORET, REH de reajuste) | C6: Nota 26.1–26.2 p. 100–101 | D6: Receita, ativos/passivos setoriais | E6: Conferir REH citadas e efeitos (nota 26.2) [Pub]
A7: Efeito direto | B7: Contratos de concessão e Decreto 12.068/2024 (renovação) | C7: Nota 1 p. 41; Fato Relevante 08/05/2026 | D7: Ativo financeiro da concessão | E7: Ler aditivos e cláusulas de indenização [P/Pub]
A8: Efeito direto | B8: Legislação tributária (IRPJ/CSLL, PIS/COFINS; tema 69 do STF — exclusão do ICMS) | C8: Nota 8 p. 62–63; nota 10 | D8: Tributos, créditos e passivos com consumidores | E8: Analítico e leitura de notas [Pub]
A9: Efeito direto | B9: CDE e subsídios tarifários (Lei 12.783/2013; Lei 14.300/2022) | C9: Nota 26.3–26.4 p. 101 | D9: Receita e contas a receber da CDE | E9: Conciliar receita CDE 3.103.700 [Pub]
A10: Outras com efeito relevante | B10: Lei 15.269/2025 (compensação por curtailment) | C10: Nota 37.2 p. 113 | D10: Ativo contingente não reconhecido | E10: Avaliar divulgação [Pub]
A11: Outras com efeito relevante | B11: Lei Anticorrupção 12.846/2013 (política anticorrupção publicada) | C11: Drive pasta 03 (Política Anticorrupção) | D11: Contingências; reputação | E11: Indagação à administração e governança [P]
A12: Outras com efeito relevante | B12: Legislação ambiental (provisões de desmobilização 175.276; incêndio — perda possível de 51.712) | C12: BP p. 35/3; nota 22 p. 95 | D12: Provisões e contingências | E12: Leitura de nota 22; cartas a advogados [Pub/P]
A13: Outras com efeito relevante | B13: Normas setoriais de qualidade (ONS/ANEEL — indicadores e penalidades) | C13: Bases ONS/CCEE (pasta 05; não validadas) | D13: Multas e compensações a consumidores | E13: Validar fonte antes de uso; indicador não prova infração [P]

Sheet Cronograma_300
A1: PT 300 — Cronograma
A2: Preparador: matrícula 231020069 (assistido por IA) | Data: 22/10/2026 | Revisão: ____ (sem revisão de terceiros simulada)
A3: Cronograma do trabalho acadêmico (prazo do enunciado: 25/10/2026).
A4: Fase | B4: Data | C4: Bloco | D4: PTs
A5: Planejamento (estratégia, riscos, materialidade) | B5: 22/10/2026 | C5: B03–B04 | D5: PT EC–230, 240, 250, 300, 315, 320, 330
A6: Grupo e prestadores | B6: 23/10/2026 | C6: B05 | D6: PT 402, 600
A7: Base sintética e testes | B7: 23/10/2026 | C7: B06–B08 | D7: PT 500, 530, 450
A8: Abertura, analíticos, estimativas, partes relacionadas | B8: 24/10/2026 | C8: B09 | D8: PT 510, 520, 540, 550
A9: Itens específicos, confirmações, eventos, continuidade | B9: 24/10/2026 | C9: B10 | D9: PT 501, 505, 560, 570
A10: Comunicações e conclusão | B10: 25/10/2026 | C10: B11 | D10: PT 260, 265, 580; fechamento 450/500
A11: Revisão e entrega | B11: 25/10/2026 | C11: B12–B13 | D11: Revisão transversal; Word/PDF; GitHub
