Workbook

Sheet Parametros
A1: Parâmetros do grupo (R$ mil)
A2: Preparador: matrícula 231020069 (assistido por IA) | Data: 22/10/2026 | Revisão: ____ (sem revisão de terceiros simulada)
A3: Materialidades do grupo vêm do PT 320 (validadas pelo aluno em 22/10/2026).
A4: Item | B4: Valor | C4: Fonte
A5: Ativo total consolidado | B5: 81099930 | C5: DF25 p. 34/2
A6: Lucro antes dos tributos consolidado | B6: 8091246 | C6: DF25 p. 36/4
A7: Materialidade global do grupo | B7: 404562.3 | C7: PT 320
A8: Materialidade para execução do grupo | B8: 303421.72 | C8: PT 320
A9: Claramente trivial do grupo | B9: 20228.115 | C9: PT 320
A10: % execução componente — componentes de maior porte | B10: 0.7 | C10: Julgamento (600 item 35(a): deve ser inferior à execução do grupo)
A11: % execução componente — demais componentes | B11: 0.5 | C11: Julgamento (maior risco de agregação em componentes menores e numerosos)

Sheet Componentes_600
A1: PT 600 — Componentes, porte relativo e abordagem (controladas diretas — nota 13.1)
A2: Preparador: matrícula 231020069 (assistido por IA) | Data: 22/10/2026 | Revisão: ____ (sem revisão de terceiros simulada)
A3: Ativo e resultado: DF25 nota 13.1, p. 70/38 (informação individual de cada controlada; inclui investimentos em outras controladas — há sobreposição, por isso as proporções são indicativas e não somam 100%). Classificação = julgamento do auditor do grupo (NBC TA 600 R2 não usa mais a categoria 'componente significativo' da versão anterior; usa-se o risco e a agregação — itens 22, 33, 35).
A4: Componente | B4: Segmento | C4: Ativo total (individual) | D4: Resultado 2025 | E4: Ativo / ativo consolidado | F4: |Resultado| / LAIR consolidado | G4: Classificação (julgamento) | H4: Abordagem planejada | I4: Mat. execução do componente | J4: Limite de comunicação | K4: Auditor do componente (fonte)
A5: CPFL Paulista | B5: Distribuição | C5: 22954592 | D5: 1864350 | E5: =C5/Parametros!$B$5 -> 0.28304084 | F5: =ABS(D5)/Parametros!$B$6 -> 0.23041569 | G5: Maior porte | H5: Procedimentos de auditoria nas informações financeiras completas (ativo financeiro da concessão, receita não faturada) | I5: =Parametros!$B$8*Parametros!$B$10 -> 212395.21 | J5: =Parametros!$B$9 -> 20228.115 | K5: PwC — relatório 04/03/2026 (DF Paulista)
A6: CPFL RGE | B6: Distribuição | C6: 21762223 | D6: 1327456 | E6: =C6/Parametros!$B$5 -> 0.26833837 | F6: =ABS(D6)/Parametros!$B$6 -> 0.16406076 | G6: Maior porte | H6: Idem | I6: =Parametros!$B$8*Parametros!$B$10 -> 212395.21 | J6: =Parametros!$B$9 -> 20228.115 | K6: PwC — opinião sem modificação; data não localizada no texto extraído (DF RGE)
A7: CPFL Piratininga | B7: Distribuição | C7: 8226299 | D7: 548281 | E7: =C7/Parametros!$B$5 -> 0.10143411 | F7: =ABS(D7)/Parametros!$B$6 -> 0.067762246 | G7: Porte médio | H7: Procedimentos sobre saldos de risco (ativo financeiro da concessão, receita, dívida) | I7: =Parametros!$B$8*Parametros!$B$11 -> 151710.86 | J7: =Parametros!$B$9 -> 20228.115 | K7: PwC — 04/03/2026 (DF Piratininga)
A8: CPFL Santa Cruz | B8: Distribuição | C8: 2647005 | D8: 130563 | E8: =C8/Parametros!$B$5 -> 0.032638807 | F8: =ABS(D8)/Parametros!$B$6 -> 0.016136328 | G8: Porte menor | H8: Procedimentos sobre ativo financeiro da concessão (base sintética inclui) + analíticos | I8: =Parametros!$B$8*Parametros!$B$11 -> 151710.86 | J8: =Parametros!$B$9 -> 20228.115 | K8: Não verificado (DF não disponível no Drive)
A9: CPFL Transmissão | B9: Transmissão | C9: 9425400 | D9: 268600 | E9: =C9/Parametros!$B$5 -> 0.11621958 | F9: =ABS(D9)/Parametros!$B$6 -> 0.03319637 | G9: Porte médio | H9: Procedimentos sobre ativo contratual (PAA 1) e receita de remuneração | I9: =Parametros!$B$8*Parametros!$B$11 -> 151710.86 | J9: =Parametros!$B$9 -> 20228.115 | K9: PwC — 04/03/2026 (DF Transmissão)
A10: CPFL Renováveis | B10: Geração | C10: 8335380 | D10: 1062034 | E10: =C10/Parametros!$B$5 -> 0.10277913 | F10: =ABS(D10)/Parametros!$B$6 -> 0.13125716 | G10: Porte médio | H10: Procedimentos sobre imobilizado/intangível e receita de geração | I10: =Parametros!$B$8*Parametros!$B$11 -> 151710.86 | J10: =Parametros!$B$9 -> 20228.115 | K10: PwC — 04/03/2026 (DF Renováveis)
A11: CPFL Geração | B11: Geração | C11: 3461790 | D11: 1129886 | E11: =C11/Parametros!$B$5 -> 0.042685487 | F11: =ABS(D11)/Parametros!$B$6 -> 0.13964302 | G11: Porte menor (holding de geração) | H11: Analíticos + equivalência de controladas em conjunto; incorporada em 02/02/2026 (nota 37.1) | I11: =Parametros!$B$8*Parametros!$B$11 -> 151710.86 | J11: =Parametros!$B$9 -> 20228.115 | K11: Não verificado
A12: CPFL Brasil | B12: Comercialização | C12: 4855998 | D12: 142279 | E12: =C12/Parametros!$B$5 -> 0.059876722 | F12: =ABS(D12)/Parametros!$B$6 -> 0.017584313 | G12: Porte menor | H12: Corte de receita de comercialização (CCEE) + analíticos | I12: =Parametros!$B$8*Parametros!$B$11 -> 151710.86 | J12: =Parametros!$B$9 -> 20228.115 | K12: Não verificado
A13: CPFL Serviços e entidades de serviços compartilhados (Atende, Infra, Pessoas, Finanças, Supri, AUTHI, Telecom, Planalto, Jaguari Geração, Alesta, Clion) | B13: Serviços/outros | C13: 1163319 | D13: 206407 | E13: =C13/Parametros!$B$5 -> 0.014344266 | F13: =ABS(D13)/Parametros!$B$6 -> 0.025509915 | G13: Agregado pouco relevante individualmente | H13: Analíticos no nível do grupo; atenção a funções compartilhadas (finanças, pessoas, suprimentos) que afetam vários componentes | I13: =Parametros!$B$8*Parametros!$B$11 -> 151710.86 | J13: =Parametros!$B$9 -> 20228.115 | K13: Não verificado
A15: Controladas em conjunto (equivalência patrimonial; nota 13.9.3, p. 74): BAESA (25,01%) e Chapecoense (51% — controle conjunto por acordo de acionistas) | B15: Geração/Transmissão | C15: 380803 | D15: 275980 | E15: =C15/Parametros!$B$5 -> 0.0046954788 | F15: =ABS(D15)/Parametros!$B$6 -> 0.034108467 | G15: Equivalência patrimonial | H15: Ler acordo de acionistas (julgamento de controle conjunto); obter DF auditadas; recalcular equivalência | I15: — | J15: — | K15: Não verificado

Sheet Segmentos_nota30
A1: Nota 30 — Informações por segmento 2025 (R$ mil)
A2: Preparador: matrícula 231020069 (assistido por IA) | Data: 22/10/2026 | Revisão: ____ (sem revisão de terceiros simulada)
A3: Fonte: DF25 nota 30, p. 103/71 (tabela em imagem; transcrição conferida pelos totais).
A4: Segmento | B4: Receita líquida | C4: Lucro antes dos impostos | D4: Aquisições de ativo contratual, imobilizado e intangível | E4: % do LAIR consolidado
A5: Distribuição | B5: 36531151 | C5: 5331500 | D5: 4963868 | E5: =C5/Parametros!$B$6 -> 0.658922
A6: Geração | B6: 3272911 | C6: 2547712 | D6: 269975 | E6: =C6/Parametros!$B$6 -> 0.31487264
A7: Transmissão | B7: 1635891 | C7: 350619 | D7: 804090 | E7: =C7/Parametros!$B$6 -> 0.043333128
A8: Comercialização | B8: 2692087 | C8: -281094 | D8: 1500 | E8: =C8/Parametros!$B$6 -> -0.034740508
A9: Serviços | B9: 234086 | C9: 259335 | D9: 71632 | E9: =C9/Parametros!$B$6 -> 0.032051306
A10: Outros | B10: 1655 | C10: -116826 | D10: 1033 | E10: =C10/Parametros!$B$6 -> -0.014438567
A11: Soma (calculada) | B11: =SUM(B5:B10) -> 44367781 | C11: =SUM(C5:C10) -> 8091246 | D11: =SUM(D5:D10) -> 6112098
A12: Divulgado (total consolidado) | B12: 44367780 | C12: 8091246 | D12: 6112098
A13: Diferença | B13: =B11-B12 -> 1 | C13: =C11-C12 -> 0 | D13: =D11-D12 -> 0 | E13: esperado 0/±1 (eliminações entre segmentos já líquidas na receita)

Sheet Prestadores_402
A1: PT 402 — Organizações prestadoras de serviços relevantes
A2: Preparador: matrícula 231020069 (assistido por IA) | Data: 22/10/2026 | Revisão: ____ (sem revisão de terceiros simulada)
A3: Identificação a partir das notas. 'Documentado' = citado na DF25; 'Hipótese' = serviço típico do setor, não comprovado. Nenhum relatório de asseguração de prestador foi obtido.
A4: Prestador / serviço | B4: Situação documental | C4: Fonte | D4: Processo e afirmações afetadas | E4: Relevante para as DF? | F4: Relatório tipo 1/2 disponível? | G4: Controles complementares da entidade usuária (exemplos) | H4: Procedimento planejado / alternativo | I4: Modalidade
A5: Vivest e Fundação Família Previdência — administração dos planos de previdência e dos ativos garantidores | B5: Documentado | C5: DF25 nota 20, p. 86 e 92 | D5: Obrigação atuarial (606.924 no BP) e ativos do plano; avaliação, existência | E5: Sim | F5: Não obtido | G5: Envio de cadastro de participantes; conciliação de contribuições; aprovação de premissas atuariais | H5: Obter relatório do auditor do plano e confirmação dos ativos; testar dados censitários; usar especialista atuário (NBC TA 620) | I5: Planejado por falta de acesso
A6: CCEE — contabilização e liquidação do mercado de curto prazo | B6: Documentado | C6: DF25 nota 3.11, p. 54; nota 12 | D6: Receita e custo de energia (comercialização, liquidação); ocorrência, exatidão | E6: Sim | F6: Não obtido (não verificado se existe) | G6: Conferência dos relatórios de pré-liquidação; registro de contratos bilaterais | H6: Conciliar relatórios de liquidação da CCEE com a contabilidade; inspecionar registros de contratos (planejado); usar dados abertos da CCEE apenas após validação da fonte (P07) | I6: Planejado por falta de acesso
A7: Empreiteiras de construção da infraestrutura (alto grau de terceirização) | B7: Documentado | C7: DF25 nota 3, p. 47 | D7: Ativo contratual e receita/custo de construção (5.879.424 / 5.566.883); existência, exatidão, corte | E7: Sim (afeta ativos da concessão) | F7: Não aplicável (prestador operacional, não processa informação contábil) | G7: Medição de obras e aceite; controle de ordens de serviço | H7: Tratar como fornecedor (NBC TA 500): inspeção de medições e contratos; a NBC TA 402 só se aplica se o prestador processar informação que integra o sistema de informação | I7: Planejado por falta de acesso
A8: Agentes arrecadadores (bancos) — cobrança das faturas e convênios de arrecadação | B8: Documentado em parte (convênios de arrecadação na nota 23, p. 97); bancos = hipótese | C8: DF25 nota 23, p. 97 | D8: Contas a receber e caixa; existência, corte | E8: Sim | F8: Não obtido | G8: Conciliação diária de arquivos de retorno bancário | H8: Conciliar arquivos de retorno × baixas de contas a receber; confirmação bancária (PT 505) | I8: Planejado por falta de acesso
A9: Provedores de TI/nuvem (ERP, faturamento, medição) | B9: Hipótese (não identificado na DF25) | C9: — | D9: Receita não faturada e faturamento (R03, R15) | E9: A confirmar | F9: Não obtido | G9: Gestão de acessos e mudanças do lado da entidade | H9: Indagar à administração sobre terceirização de TI; se houver, obter relatório tipo 2 com período coberto e avaliar exceções e subcontratadas (402 itens 13–18) | I9: Planejado por falta de acesso
A10: Centros de serviços compartilhados do próprio grupo (CPFL Serviços, Finanças, Pessoas, Supri, Atende) | B10: Documentado (entidades do grupo) | C10: DF25 nota 13.1, p. 70/38 | D10: Folha, finanças, suprimentos, atendimento | E10: Sim — mas são componentes do grupo, não prestadores externos | F10: Não aplicável | G10: — | H10: Tratar no PT 600 (funções compartilhadas), não na NBC TA 402 | I10: Realizado com evidência pública (classificação)
